germqtt/__init__.py
germqtt/germqtt.py
germqtt/tests/__init__.py
germqtt/tests/base.py
germqtt/tests/test_germqtt.py
germqtt-0.1.0.dist-info/DESCRIPTION.rst
germqtt-0.1.0.dist-info/METADATA
germqtt-0.1.0.dist-info/RECORD
germqtt-0.1.0.dist-info/WHEEL
germqtt-0.1.0.dist-info/entry_points.txt
germqtt-0.1.0.dist-info/metadata.json
germqtt-0.1.0.dist-info/pbr.json
germqtt-0.1.0.dist-info/top_level.txt
