Metadata-Version: 2.0
Name: germqtt
Version: 0.1.0
Summary: Publish Gerrit Stream on MQTT
Home-page: UNKNOWN
Author: Matthew Treinish
Author-email: mtreinish@kortar.org
License: UNKNOWN
Platform: UNKNOWN
Classifier: Intended Audience :: Information Technology
Classifier: Intended Audience :: System Administrators
Classifier: Intended Audience :: Developers
Classifier: License :: OSI Approved :: Apache Software License
Classifier: Operating System :: POSIX :: Linux
Classifier: Programming Language :: Python
Classifier: Programming Language :: Python :: 2
Classifier: Programming Language :: Python :: 2.7
Classifier: Programming Language :: Python :: 3
Classifier: Programming Language :: Python :: 3.4
Requires-Dist: gerritlib (>=0.6.0)
Requires-Dist: paho-mqtt (>=1.1)
Requires-Dist: pbr (>=1.6)
Requires-Dist: python-daemon
Requires-Dist: six (>=1.9.0)
